dropbot_dx/__init__.py
dropbot_dx/config.py
dropbot_dx/node.py
dropbot_dx/proxy.py
dropbot_dx/state.py
dropbot_dx/Arduino/dropbot_dx/Node.cpp
dropbot_dx/Arduino/dropbot_dx/Node.h
dropbot_dx/Arduino/dropbot_dx/NodeCommandProcessor.h
dropbot_dx/Arduino/dropbot_dx/RPCBuffer.h
dropbot_dx/Arduino/dropbot_dx/RPCBuffer.ht
dropbot_dx/Arduino/dropbot_dx/SConscript
dropbot_dx/Arduino/dropbot_dx/aligned_alloc.h
dropbot_dx/Arduino/dropbot_dx/config.options
dropbot_dx/Arduino/dropbot_dx/config.proto
dropbot_dx/Arduino/dropbot_dx/dropbot_dx.ino
dropbot_dx/Arduino/dropbot_dx/dropbot_dx_config_validate.h
dropbot_dx/Arduino/dropbot_dx/dropbot_dx_state_validate.h
dropbot_dx/Arduino/dropbot_dx/state.proto
dropbot_dx/Arduino/library/DropbotDx.zip
dropbot_dx/Arduino/library/DropbotDx/library.properties
dropbot_dx/Arduino/library/DropbotDx/src/DropbotDx.h
dropbot_dx/Arduino/library/DropbotDx/src/DropbotDx/CommandProcessor.h
dropbot_dx/Arduino/library/DropbotDx/src/DropbotDx/Commands.h
dropbot_dx/Arduino/library/DropbotDx/src/DropbotDx/Properties.h
dropbot_dx/Arduino/library/DropbotDx/src/DropbotDx/config_pb.c
dropbot_dx/Arduino/library/DropbotDx/src/DropbotDx/config_pb.h
dropbot_dx/Arduino/library/DropbotDx/src/DropbotDx/state_pb.c
dropbot_dx/Arduino/library/DropbotDx/src/DropbotDx/state_pb.h
dropbot_dx/bin/__init__.py
dropbot_dx/bin/upload.py
dropbot_dx/static/data/adc_configs.h5
dropbot_dx-1.2.post2.dist-info/DESCRIPTION.rst
dropbot_dx-1.2.post2.dist-info/METADATA
dropbot_dx-1.2.post2.dist-info/RECORD
dropbot_dx-1.2.post2.dist-info/WHEEL
dropbot_dx-1.2.post2.dist-info/metadata.json
dropbot_dx-1.2.post2.dist-info/top_level.txt
