Metadata-Version: 2.0
Name: dropbot-dx
Version: 1.2.post2
Summary: Template project demonstrating use of Arduino base node RPC framework.
Home-page: http://github.com/wheeler-microfluidics/dropbot-dx.git
Author: Christian Fobel
Author-email: christian@fobel.net
License: GPLv2
Platform: UNKNOWN
Requires-Dist: arduino-rpc (>=1.7.post20)
Requires-Dist: base-node-rpc (>=0.16.post3)
Requires-Dist: serial-device (>=0.3)
